trytond/modules/health_services/COPYING
trytond/modules/health_services/README.rst
trytond/modules/health_services/__init__.py
trytond/modules/health_services/data/gnuhealth_commands.xml
trytond/modules/health_services/data/health_service_sequences.xml
trytond/modules/health_services/data/health_services_data.xml
trytond/modules/health_services/data/messages/messages.xml
trytond/modules/health_services/exceptions.py
trytond/modules/health_services/health_services.py
trytond/modules/health_services/health_services_report.xml
trytond/modules/health_services/health_services_view.xml
trytond/modules/health_services/icons/folder-documents.svg
trytond/modules/health_services/icons/tryton-financial.svg
trytond/modules/health_services/invoice.py
trytond/modules/health_services/invoice.xml
trytond/modules/health_services/locale/ar.po
trytond/modules/health_services/locale/de.po
trytond/modules/health_services/locale/el.po
trytond/modules/health_services/locale/eo.po
trytond/modules/health_services/locale/es.po
trytond/modules/health_services/locale/fr.po
trytond/modules/health_services/locale/health_services.pot
trytond/modules/health_services/locale/it_IT.po
trytond/modules/health_services/locale/ja_JP.po
trytond/modules/health_services/locale/ka.po
trytond/modules/health_services/locale/lo.po
trytond/modules/health_services/locale/pt_BR.po
trytond/modules/health_services/locale/sv.po
trytond/modules/health_services/locale/tr.po
trytond/modules/health_services/locale/uk.po
trytond/modules/health_services/locale/zh_CN.po
trytond/modules/health_services/pyproject.toml
trytond/modules/health_services/report/health_services_report.fodt
trytond/modules/health_services/security/access_rights.xml
trytond/modules/health_services/sequences.py
trytond/modules/health_services/tests/__init__.py
trytond/modules/health_services/tests/test_health_services.py
trytond/modules/health_services/tryton.cfg
trytond/modules/health_services/view/gnuhealth_health_service.xml
gnuhealth_services-5.0.2.dist-info/METADATA
gnuhealth_services-5.0.2.dist-info/WHEEL
gnuhealth_services-5.0.2.dist-info/licenses/COPYING
gnuhealth_services-5.0.2.dist-info/RECORD
